azure/mgmt/resource/__init__.py
azure/mgmt/resource/_version.py
azure/mgmt/resource/py.typed
azure/mgmt/resource/changes/__init__.py
azure/mgmt/resource/changes/_changes_client.py
azure/mgmt/resource/changes/_configuration.py
azure/mgmt/resource/changes/_serialization.py
azure/mgmt/resource/changes/_version.py
azure/mgmt/resource/changes/models.py
azure/mgmt/resource/changes/py.typed
azure/mgmt/resource/changes/aio/__init__.py
azure/mgmt/resource/changes/aio/_changes_client.py
azure/mgmt/resource/changes/aio/_configuration.py
azure/mgmt/resource/changes/v2022_05_01/__init__.py
azure/mgmt/resource/changes/v2022_05_01/_changes_client.py
azure/mgmt/resource/changes/v2022_05_01/_configuration.py
azure/mgmt/resource/changes/v2022_05_01/_patch.py
azure/mgmt/resource/changes/v2022_05_01/_version.py
azure/mgmt/resource/changes/v2022_05_01/py.typed
azure/mgmt/resource/changes/v2022_05_01/aio/__init__.py
azure/mgmt/resource/changes/v2022_05_01/aio/_changes_client.py
azure/mgmt/resource/changes/v2022_05_01/aio/_configuration.py
azure/mgmt/resource/changes/v2022_05_01/aio/_patch.py
azure/mgmt/resource/changes/v2022_05_01/aio/operations/__init__.py
azure/mgmt/resource/changes/v2022_05_01/aio/operations/_operations.py
azure/mgmt/resource/changes/v2022_05_01/aio/operations/_patch.py
azure/mgmt/resource/changes/v2022_05_01/models/__init__.py
azure/mgmt/resource/changes/v2022_05_01/models/_changes_client_enums.py
azure/mgmt/resource/changes/v2022_05_01/models/_models_py3.py
azure/mgmt/resource/changes/v2022_05_01/models/_patch.py
azure/mgmt/resource/changes/v2022_05_01/operations/__init__.py
azure/mgmt/resource/changes/v2022_05_01/operations/_operations.py
azure/mgmt/resource/changes/v2022_05_01/operations/_patch.py
azure/mgmt/resource/databoundaries/__init__.py
azure/mgmt/resource/databoundaries/_configuration.py
azure/mgmt/resource/databoundaries/_data_boundary_mgmt_client.py
azure/mgmt/resource/databoundaries/_serialization.py
azure/mgmt/resource/databoundaries/_version.py
azure_mgmt_resource-23.2.0.dist-info/LICENSE
azure_mgmt_resource-23.2.0.dist-info/METADATA
azure_mgmt_resource-23.2.0.dist-info/WHEEL
azure_mgmt_resource-23.2.0.dist-info/top_level.txt
azure_mgmt_resource-23.2.0.dist-info/RECORD
